demo/__init__.py
demo/demo_launcher.py
sacreeos/__init__.py
sacreeos/__main__.py
sacreeos/cli.py
sacreeos/main.py
sacreeos/scst.py
sacreeos/err/__init__.py
sacreeos/err/commonechecks.py
sacreeos/err/commonerr.py
sacreeos/metric/__init__.py
sacreeos/metric/bleu.py
sacreeos/metric/cider.py
sacreeos/metric/cider_d.py
sacreeos/metric/cider_r.py
sacreeos/metric/metric.py
sacreeos/metric/c_core/__init__.py
sacreeos/metric/c_core/invoker.py
sacreeos/metric/py_core/__init__.py
sacreeos/metric/py_core/ngram_utils.py
sacreeos/metric/py_core/py_bleu_scorer.py
sacreeos/metric/py_core/py_cider_scorer.py
sacreeos/reward_base/__init__.py
sacreeos/reward_base/average.py
sacreeos/reward_base/base.py
sacreeos/reward_base/greedy.py
sacreeos/scst_conf/__init__.py
sacreeos/scst_conf/conf.py
sacreeos/scst_conf/noeos.py
sacreeos/scst_conf/standard.py
sacreeos/utils/__init__.py
sacreeos/utils/cli_args.py
testing/__init__.py
testing/test_input.py
testing/test_manual.py
testing/test_metrics.py
testing/test_signatures.py
testing/test_speed.py
testing/test_training.py
sacreeos-1.0.2.dist-info/LICENSE.txt
sacreeos-1.0.2.dist-info/METADATA
sacreeos-1.0.2.dist-info/WHEEL
sacreeos-1.0.2.dist-info/entry_points.txt
sacreeos-1.0.2.dist-info/top_level.txt
sacreeos-1.0.2.dist-info/RECORD
