Metadata-Version: 2.1
Name: sacreeos
Version: 1.0.2
Summary: SacreEOS is a signature generator and implementation helper for the Self Critical Sequence Training
Home-page: https://github.com/jchenghu/sacreeos
Author: Jia Cheng Hu
Author-email: jia.jiachenghu@gmail.com
License: Apache License 2.0
Keywords: self-critical sequence training, computer vision, image captioning, evaluation
Classifier: Intended Audience :: Developers
Classifier: Intended Audience :: Science/Research
Classifier: Topic :: Scientific/Engineering :: Artificial Intelligence
Classifier: License :: OSI Approved :: Apache Software License
Classifier: Operating System :: POSIX
Classifier: Programming Language :: C++
Classifier: Programming Language :: Python :: 3 :: Only
Requires-Python: >=3.7
License-File: LICENSE.txt
Requires-Dist: torch
Requires-Dist: numpy
Requires-Dist: typing
